grand-0.20.dist-info/COPYING.LESSER
grand-0.20.dist-info/RECORD
grand-0.20.dist-info/METADATA
grand-0.20.dist-info/top_level.txt
grand-0.20.dist-info/WHEEL
grand-0.20.dist-info/LICENSE
grand.libs/libpng16-54bb6326.so.16.35.0
grand.libs/libturtle-747a6a0b.so
grand.libs/libz-a147dcb0.so.1.2.3
grand.libs/libgull-d80c5c13.so
grand/logging.py
grand/__init__.py
grand/version.py
grand/_core.abi3.so
grand/io.py
grand/libs/turtle.py
grand/libs/gull.py
grand/libs/__init__.py
grand/libs/data/gull/WMM2020.COF
grand/libs/data/gull/IGRF13.COF
grand/store/__init__.py
grand/store/protocol.py
grand/tools/__init__.py
grand/tools/geomagnet.py
grand/tools/topography.py
grand/tools/data/egm96.png
grand/tools/coordinates/__init__.py
grand/tools/coordinates/transform.py
grand/tools/coordinates/representation.py
grand/tools/coordinates/frame.py
grand/simulation/__init__.py
grand/simulation/pdg.py
grand/simulation/shower/__init__.py
grand/simulation/shower/coreas.py
grand/simulation/shower/generic.py
grand/simulation/shower/zhaires.py
grand/simulation/antenna/__init__.py
grand/simulation/antenna/tabulated.py
grand/simulation/antenna/generic.py
