Metadata-Version: 2.1
Name: grand
Version: 0.20
Summary: Core package for GRAND
Home-page: https://github.com/grand-mother/grand
Maintainer: GRAND developers
Maintainer-email: grand-dev@googlegroups.com
License: LGPLv3
Download-URL: https://pypi.python.org/pypi/grand
Project-URL: Bug Tracker, https://github.com/grand-mother/grand/issues
Project-URL: Documentation, https://https://grand-mother.github.io/grand-docs
Project-URL: Source Code, https://github.com/grand-mother/grand
Platform: Linux
Platform: Mac OS-X
Classifier: Development Status :: 4 - Beta
Classifier: Intended Audience :: Science/Research
Classifier: License :: OSI Approved :: GNU Lesser General Public License v3 (LGPLv3)
Classifier: Programming Language :: C
Classifier: Programming Language :: Python :: 3.8
Classifier: Programming Language :: Python :: Implementation :: CPython
Classifier: Topic :: Scientific/Engineering
Classifier: Operating System :: POSIX :: Linux
Classifier: Operating System :: MacOS
Requires-Python: >=3.8
License-File: LICENSE
License-File: COPYING.LESSER
Requires-Dist: astropy
Requires-Dist: cffi
Requires-Dist: h5py
Requires-Dist: numpy
Requires-Dist: scipy
Requires-Dist: typing-extensions
